manage.py
dj_email_support/__init__.py
dj_email_support/asgi.py
dj_email_support/manage.py
dj_email_support/settings.py
dj_email_support/urls.py
dj_email_support/wsgi.py
index/__init__.py
index/admin.py
index/apps.py
index/models.py
index/serializers.py
index/tests.py
index/urls.py
index/views.py
index/migrations/0001_initial.py
index/migrations/__init__.py
drf_support_emails_chilusoft-0.0.1.dist-info/LICENSE
drf_support_emails_chilusoft-0.0.1.dist-info/METADATA
drf_support_emails_chilusoft-0.0.1.dist-info/WHEEL
drf_support_emails_chilusoft-0.0.1.dist-info/top_level.txt
drf_support_emails_chilusoft-0.0.1.dist-info/RECORD
