Metadata-Version: 2.1
Name: drf_support_emails_chilusoft
Version: 0.0.1
Summary: A DRF implementation of Contact Support Emails
Author-email: Chilufya Mukuka <mukukachilu@gmail.com>
Project-URL: Homepage, https://github.com/chilusoft/django-support-emails/
Project-URL: Issues, https://github.com/chilusoft/django-support-emails/issues
Classifier: Programming Language :: Python :: 3
Classifier: License :: OSI Approved :: MIT License
Classifier: Operating System :: OS Independent
Requires-Python: >=3.8
License-File: LICENSE
